{
  "micros": {
    "duration_phases_______________": 166220,
    "duration_phases_with_extra____": 742870,
    "phase_1_1_factorization_icfl__": 3331,
    "phase_1_2_factorization_custom": 253,
    "phase_2_1_trie_create_________": 66138,
    "phase_2_2_trie_merge_rankings_": 32242,
    "phase_2_3_trie_in_prefix_merge": 45060,
    "phase_2_4_tree_create_________": 10657,
    "phase_3_0_suffix_array________": 8537
  },
  "seconds": {
    "duration_phases_______________": 0.166,
    "duration_phases_with_extra____": 0.743,
    "phase_1_1_factorization_icfl__": 0.003,
    "phase_1_2_factorization_custom": 0.0,
    "phase_2_1_trie_create_________": 0.066,
    "phase_2_2_trie_merge_rankings_": 0.032,
    "phase_2_3_trie_in_prefix_merge": 0.045,
    "phase_2_4_tree_create_________": 0.011,
    "phase_3_0_suffix_array________": 0.009
  },
  "percentages": {
    "phase_1_1_factorization_icfl__": 2,
    "phase_1_2_factorization_custom": 0,
    "phase_2_1_trie_create_________": 40,
    "phase_2_2_trie_merge_rankings_": 19,
    "phase_2_3_trie_in_prefix_merge": 27,
    "phase_2_4_tree_create_________": 6,
    "phase_3_0_suffix_array________": 6
  }
}