{
  "micros": {
    "duration_phases_______________": 130972,
    "duration_phases_with_extra____": 534069,
    "phase_1_1_factorization_icfl__": 2351,
    "phase_1_2_factorization_custom": 135,
    "phase_2_1_trie_create_________": 73488,
    "phase_2_2_trie_merge_rankings_": 18682,
    "phase_2_3_trie_in_prefix_merge": 17211,
    "phase_2_4_tree_create_________": 10604,
    "phase_3_0_suffix_array________": 8497
  },
  "seconds": {
    "duration_phases_______________": 0.131,
    "duration_phases_with_extra____": 0.534,
    "phase_1_1_factorization_icfl__": 0.002,
    "phase_1_2_factorization_custom": 0.0,
    "phase_2_1_trie_create_________": 0.073,
    "phase_2_2_trie_merge_rankings_": 0.019,
    "phase_2_3_trie_in_prefix_merge": 0.017,
    "phase_2_4_tree_create_________": 0.011,
    "phase_3_0_suffix_array________": 0.008
  },
  "percentages": {
    "phase_1_1_factorization_icfl__": 2,
    "phase_1_2_factorization_custom": 0,
    "phase_2_1_trie_create_________": 56,
    "phase_2_2_trie_merge_rankings_": 14,
    "phase_2_3_trie_in_prefix_merge": 13,
    "phase_2_4_tree_create_________": 8,
    "phase_3_0_suffix_array________": 7
  }
}