{
  "micros": {
    "duration_phases_______________": 981879,
    "duration_phases_with_extra____": 5147477,
    "phase_1_1_factorization_icfl__": 28704,
    "phase_1_2_factorization_custom": 2252,
    "phase_2_1_trie_create_________": 425698,
    "phase_2_2_shrink______________": 0,
    "phase_2_3_in_prefix_merge_____": 299915,
    "phase_3_0_suffix_array________": 225308
  },
  "seconds": {
    "duration_phases_______________": 0.982,
    "duration_phases_with_extra____": 5.147,
    "phase_1_1_factorization_icfl__": 0.029,
    "phase_1_2_factorization_custom": 0.002,
    "phase_2_1_trie_create_________": 0.426,
    "phase_2_2_shrink______________": 0.0,
    "phase_2_3_in_prefix_merge_____": 0.3,
    "phase_3_0_suffix_array________": 0.225
  },
  "percentages": {
    "phase_1_1_factorization_icfl__": 3,
    "phase_1_2_factorization_custom": 0,
    "phase_2_1_trie_create_________": 43,
    "phase_2_2_shrink______________": 0,
    "phase_2_3_in_prefix_merge_____": 31,
    "phase_3_0_suffix_array________": 23
  }
}