{
  "micros": {
    "duration_phases_______________": 1883864,
    "duration_phases_with_extra____": 5739280,
    "phase_1_1_factorization_icfl__": 29715,
    "phase_1_2_factorization_custom": 2113,
    "phase_2_1_trie_create_________": 1005326,
    "phase_2_2_trie_merge_rankings_": 253380,
    "phase_2_3_trie_in_prefix_merge": 252288,
    "phase_2_4_tree_create_________": 199313,
    "phase_3_0_suffix_array________": 141726
  },
  "seconds": {
    "duration_phases_______________": 1.884,
    "duration_phases_with_extra____": 5.739,
    "phase_1_1_factorization_icfl__": 0.03,
    "phase_1_2_factorization_custom": 0.002,
    "phase_2_1_trie_create_________": 1.005,
    "phase_2_2_trie_merge_rankings_": 0.253,
    "phase_2_3_trie_in_prefix_merge": 0.252,
    "phase_2_4_tree_create_________": 0.199,
    "phase_3_0_suffix_array________": 0.142
  },
  "percentages": {
    "phase_1_1_factorization_icfl__": 2,
    "phase_1_2_factorization_custom": 0,
    "phase_2_1_trie_create_________": 53,
    "phase_2_2_trie_merge_rankings_": 13,
    "phase_2_3_trie_in_prefix_merge": 13,
    "phase_2_4_tree_create_________": 11,
    "phase_3_0_suffix_array________": 8
  }
}